{"link": [], "file_urls": ["http://www.cnmods.org"], "title": []}
{"link": ["mods/dnd/Warehouse.rar"], "file_urls": ["http://www.cnmods.org/mods/dnd/Warehouse.rar"], "title": ["废土残生：山间仓库"]}
{"link": ["mods/coc/isLand1.rar"], "file_urls": ["http://www.cnmods.org/mods/coc/isLand1.rar"], "title": ["涠洲岛第一部"]}
{"link": ["mods/coc/Cold_Harvest.rar"], "file_urls": ["http://www.cnmods.org/mods/coc/Cold_Harvest.rar"], "title": ["冰冷的收获"]}
{"link": ["mods/dnd/The_murderer.rar"], "file_urls": ["http://www.cnmods.org/mods/dnd/The_murderer.rar"], "title": ["谁是真凶"]}
{"link": ["mods/dnd/The_castle.rar"], "file_urls": ["http://www.cnmods.org/mods/dnd/The_castle.rar"], "title": ["古堡惊魂"]}
{"link": ["mods/dnd/3rdEnemy.rar"], "file_urls": ["http://www.cnmods.org/mods/dnd/3rdEnemy.rar"], "title": ["第三章：熟悉的敌人"]}
{"link": ["mods/coc/TheKingofShredsandPatches.rar"], "file_urls": ["http://www.cnmods.org/mods/coc/TheKingofShredsandPatches.rar"], "title": ["褴褛之王"]}
{"link": ["mods/coc/toryanse_zh_cn.rar"], "file_urls": ["http://www.cnmods.org/mods/coc/toryanse_zh_cn.rar"], "title": ["通过吧"]}
{"link": ["mods/coc/TheGardenofEarthlyDelights.rar"], "file_urls": ["http://www.cnmods.org/mods/coc/TheGardenofEarthlyDelights.rar"], "title": ["人间乐土"]}
{"link": ["mods/dnd/2ndwolf.rar"], "file_urls": ["http://www.cnmods.org/mods/dnd/2ndwolf.rar"], "title": ["第二章：迅狼的袭击"]}
{"link": ["mods/coc/lifeofdrink.rar"], "file_urls": ["http://www.cnmods.org/mods/coc/lifeofdrink.rar"], "title": ["永生之酒"]}
{"link": ["mods/coc/substance2010.rar"], "file_urls": ["http://www.cnmods.org/mods/coc/substance2010.rar"], "title": ["谁是沼泽人"]}
{"link": ["mods/coc/time-out.rar"], "file_urls": ["http://www.cnmods.org/mods/coc/time-out.rar"], "title": ["时光之外"]}
{"link": ["mods/dnd/1stdwarf.rar"], "file_urls": ["http://www.cnmods.org/mods/dnd/1stdwarf.rar"], "title": ["序章：矮人陵墓之谜"]}
{"link": ["mods/coc/godHospital.zip"], "file_urls": ["http://www.cnmods.org/mods/coc/godHospital.zip"], "title": ["神赦医院"]}
{"link": ["mods/dnd/hotPlague.zip"], "file_urls": ["http://www.cnmods.org/mods/dnd/hotPlague.zip"], "title": ["热瘟"]}
{"link": ["mods/coc/fire.zip"], "file_urls": ["http://www.cnmods.org/mods/coc/fire.zip"], "title": ["地狱之火"]}
{"link": ["mods/dnd/4E-Disaster.zip"], "file_urls": ["http://www.cnmods.org/mods/dnd/4E-Disaster.zip"], "title": ["包藏祸心"]}
{"link": ["mods/dnd/L&D-V1.zip"], "file_urls": ["http://www.cnmods.org/mods/dnd/L&D-V1.zip"], "title": ["光与暗"]}
{"link": ["mods/dnd/Pit-V1.zip"], "file_urls": ["http://www.cnmods.org/mods/dnd/Pit-V1.zip"], "title": ["矿坑"]}
{"link": ["mods/dnd/Mercury-V1.zip"], "file_urls": ["http://www.cnmods.org/mods/dnd/Mercury-V1.zip"], "title": ["一滴水银"]}
{"link": ["mods/coc/WarIIblack.rar"], "file_urls": ["http://www.cnmods.org/mods/coc/WarIIblack.rar"], "title": ["黑色行动"]}
{"link": ["mods/dnd/3emonk.zip"], "file_urls": ["http://www.cnmods.org/mods/dnd/3emonk.zip"], "title": ["无尽的修行"]}
{"link": ["mods/coc/stone.zip"], "file_urls": ["http://www.cnmods.org/mods/coc/stone.zip"], "title": ["噩梦之石"]}
{"link": ["mods/dnd/blackrose.zip"], "file_urls": ["http://www.cnmods.org/mods/dnd/blackrose.zip"], "title": ["魔域传奇-当黑玫瑰盛开时"]}
{"link": ["mods/dnd/onefqkk.zip"], "file_urls": ["http://www.cnmods.org/mods/dnd/onefqkk.zip"], "title": ["一个废弃矿坑"]}
{"link": ["mods/coc/cocdj.zip"], "file_urls": ["http://www.cnmods.org/mods/coc/cocdj.zip"], "title": ["赌局"]}
{"link": ["mods/dnd/witching_season_ch.rar"], "file_urls": ["http://www.cnmods.org/mods/dnd/witching_season_ch.rar"], "title": ["巫婆进行时"]}
{"link": ["mods/TheEmptyRoom.rar"], "file_urls": ["http://www.cnmods.org/mods/TheEmptyRoom.rar"], "title": ["空房子"]}
{"link": ["mods/dnd/AnIcyHeart.rar"], "file_urls": ["http://www.cnmods.org/mods/dnd/AnIcyHeart.rar"], "title": ["寒冰之心"]}
{"link": ["mods/dnd/155sleep.rar"], "file_urls": ["http://www.cnmods.org/mods/dnd/155sleep.rar"], "title": ["梦冢沉睡者"]}
{"link": ["mods/dnd/shipofhorror.rar"], "file_urls": ["http://www.cnmods.org/mods/dnd/shipofhorror.rar"], "title": ["恐惧之船"]}
{"link": ["mods/dnd/yrgoril.zip"], "file_urls": ["http://www.cnmods.org/mods/dnd/yrgoril.zip"], "title": ["极域冰原"]}
{"link": ["mods/coc/Lozdra.rar"], "file_urls": ["http://www.cnmods.org/mods/coc/Lozdra.rar"], "title": ["洛兹德拉"]}
{"link": ["mods/coc/sailasebook.rar"], "file_urls": ["http://www.cnmods.org/mods/coc/sailasebook.rar"], "title": ["塞拉斯的书"]}
{"link": [], "file_urls": ["http://www.cnmods.org"], "title": []}
{"link": ["mods/coc/tote.rar"], "file_urls": ["http://www.cnmods.org/mods/coc/tote.rar"], "title": ["透特的匕首"]}
{"link": ["mods/dnd/omegach.rar"], "file_urls": ["http://www.cnmods.org/mods/dnd/omegach.rar"], "title": ["终结之始"]}
{"link": ["mods/dnd/jialindx.rar"], "file_urls": ["http://www.cnmods.org/mods/dnd/jialindx.rar"], "title": ["地下神殿的秘密"]}
{"link": ["mods/coc/SweetHome.rar"], "file_urls": ["http://www.cnmods.org/mods/coc/SweetHome.rar"], "title": ["化石"]}
{"link": ["mods/coc/bookstore.rar"], "file_urls": ["http://www.cnmods.org/mods/coc/bookstore.rar"], "title": ["书店"]}
{"link": ["mods/coc/tellme.zip"], "file_urls": ["http://www.cnmods.org/mods/coc/tellme.zip"], "title": ["黄衣之王"]}
{"link": ["mods/coc/deepdream.rar"], "file_urls": ["http://www.cnmods.org/mods/coc/deepdream.rar"], "title": ["最深的梦境"]}
{"link": ["mods/coc/drakby.rar"], "file_urls": ["http://www.cnmods.org/mods/coc/drakby.rar"], "title": ["黑暗边缘"]}
{"link": ["mods/dnd/rogue.rar"], "file_urls": ["http://www.cnmods.org/mods/dnd/rogue.rar"], "title": ["阴影中的利刃"]}
{"link": ["mods/coc/dogblood.rar"], "file_urls": ["http://www.cnmods.org/mods/coc/dogblood.rar"], "title": ["腐坏之血"]}
{"link": ["mods/coc/three.rar"], "file_urls": ["http://www.cnmods.org/mods/coc/three.rar"], "title": ["三桩悲剧"]}
{"link": ["mods/coc/unegg.rar"], "file_urls": ["http://www.cnmods.org/mods/coc/unegg.rar"], "title": ["远古之卵"]}
{"link": ["mods/dnd/supernatural.rar"], "file_urls": ["http://www.cnmods.org/mods/dnd/supernatural.rar"], "title": ["灵异档案"]}
{"link": ["mods/coc/Tree.rar"], "file_urls": ["http://www.cnmods.org/mods/coc/Tree.rar"], "title": ["林中阴影"]}
{"link": ["mods/coc/Heaven.rar"], "file_urls": ["http://www.cnmods.org/mods/coc/Heaven.rar"], "title": ["天堂之水"]}
{"link": ["mods/dnd/dragonsgoblin.rar"], "file_urls": ["http://www.cnmods.org/mods/dnd/dragonsgoblin.rar"], "title": ["青红皂白"]}
{"link": ["mods/dnd/wailingcaverns.zip"], "file_urls": ["http://www.cnmods.org/mods/dnd/wailingcaverns.zip"], "title": ["哀嚎洞穴"]}
{"link": ["mods/dnd/halfnight.rar"], "file_urls": ["http://www.cnmods.org/mods/dnd/halfnight.rar"], "title": ["夜伴哭声"]}
{"link": ["mods/dnd/smalltown.rar"], "file_urls": ["http://www.cnmods.org/mods/dnd/smalltown.rar"], "title": ["小塔之役"]}
{"link": ["mods/dnd/gamefs.rar"], "file_urls": ["http://www.cnmods.org/mods/dnd/gamefs.rar"], "title": ["戏法师"]}
{"link": ["mods/dnd/jorke.rar"], "file_urls": ["http://www.cnmods.org/mods/dnd/jorke.rar"], "title": ["牌局"]}
{"link": ["mods/dnd/buildfor.rar"], "file_urls": ["http://www.cnmods.org/mods/dnd/buildfor.rar"], "title": ["建筑永恒"]}
{"link": ["mods/dnd/showth_death.rar"], "file_urls": ["http://www.cnmods.org/mods/dnd/showth_death.rar"], "title": ["影之墓穴"]}
{"link": ["mods/dnd/3e_blood.rar"], "file_urls": ["http://www.cnmods.org/mods/dnd/3e_blood.rar"], "title": ["血债血偿"]}
{"link": ["mods/coc/art-of-madness-ch.zip"], "file_urls": ["http://www.cnmods.org/mods/coc/art-of-madness-ch.zip"], "title": ["疯狂的艺术"]}
{"link": ["mods/dnd/tengoblin.zip"], "file_urls": ["http://www.cnmods.org/mods/dnd/tengoblin.zip"], "title": ["十镇冬日"]}
{"link": ["mods/dnd/3e_ghosthouse.rar"], "file_urls": ["http://www.cnmods.org/mods/dnd/3e_ghosthouse.rar"], "title": ["鬼屋魔影"]}
{"link": ["mods/dnd/3e_onedre.rar"], "file_urls": ["http://www.cnmods.org/mods/dnd/3e_onedre.rar"], "title": ["野性的呼唤"]}
{"link": ["mods/dnd/fqsz_f.rar"], "file_urls": ["http://www.cnmods.org/mods/dnd/fqsz_f.rar"], "title": ["废弃哨站"]}
[{"files": [{"url": "http://www.cnmods.org", "path": "full/e1dc25334c7bd048426e350296d2e3a2c46a2898.org", "checksum": "b5f19024aeb983189f02803b78e1bec6"}], "link": [], "file_urls": ["http://www.cnmods.org"], "title": []},
{"files": [{"url": "http://www.cnmods.org", "path": "full/e1dc25334c7bd048426e350296d2e3a2c46a2898.org", "checksum": "b5f19024aeb983189f02803b78e1bec6"}], "link": [], "file_urls": ["http://www.cnmods.org"], "title": []},
{"files": [{"url": "http://www.cnmods.org/mods/coc/isLand1.rar", "path": "full/a2e9daddc45fb195cffe911f0095b39666e0c285.rar", "checksum": "dcbadf795402dfe89480b9c51fb6580c"}], "link": ["mods/coc/isLand1.rar"], "file_urls": ["http://www.cnmods.org/mods/coc/isLand1.rar"], "title": ["\u6da0\u6d32\u5c9b\u7b2c\u4e00\u90e8"]},
{"files": [{"url": "http://www.cnmods.org/mods/dnd/3rdEnemy.rar", "path": "full/66c73f57f29a7df1e34ef842f70167f2b7125f5d.rar", "checksum": "c2fe19b18f0a31f2f7bf562740d8c3d9"}], "link": ["mods/dnd/3rdEnemy.rar"], "file_urls": ["http://www.cnmods.org/mods/dnd/3rdEnemy.rar"], "title": ["\u7b2c\u4e09\u7ae0\uff1a\u719f\u6089\u7684\u654c\u4eba"]},
{"files": [{"url": "http://www.cnmods.org/mods/coc/toryanse_zh_cn.rar", "path": "full/5a3543c082e7340197177f37fd2d8d92f56cc221.rar", "checksum": "3ccd2bc9d89d0d00d733ade901ccaff2"}], "link": ["mods/coc/toryanse_zh_cn.rar"], "file_urls": ["http://www.cnmods.org/mods/coc/toryanse_zh_cn.rar"], "title": ["\u901a\u8fc7\u5427"]},
{"files": [{"url": "http://www.cnmods.org/mods/coc/lifeofdrink.rar", "path": "full/e61ecedbe3a2e5394c81c5cf10b52423ff829da7.rar", "checksum": "be016ab92fe95b923a6079afda56b70c"}], "link": ["mods/coc/lifeofdrink.rar"], "file_urls": ["http://www.cnmods.org/mods/coc/lifeofdrink.rar"], "title": ["\u6c38\u751f\u4e4b\u9152"]},
{"files": [{"url": "http://www.cnmods.org/mods/dnd/2ndwolf.rar", "path": "full/12631e3ba98ff2c66d250c54b6cfdc61df618d17.rar", "checksum": "9c3f5efe9c100df09f7a4d70aa4734d6"}], "link": ["mods/dnd/2ndwolf.rar"], "file_urls": ["http://www.cnmods.org/mods/dnd/2ndwolf.rar"], "title": ["\u7b2c\u4e8c\u7ae0\uff1a\u8fc5\u72fc\u7684\u88ad\u51fb"]},
{"files": [{"url": "http://www.cnmods.org/mods/coc/substance2010.rar", "path": "full/ea31fc7262db10086aeb6d2296ec847c58f211b9.rar", "checksum": "1c24093d200755a6c9f71194ea03e363"}], "link": ["mods/coc/substance2010.rar"], "file_urls": ["http://www.cnmods.org/mods/coc/substance2010.rar"], "title": ["\u8c01\u662f\u6cbc\u6cfd\u4eba"]},
{"files": [{"url": "http://www.cnmods.org/mods/coc/time-out.rar", "path": "full/8909863b3b23ce3c2235b4487fd72339614aa0c1.rar", "checksum": "62a35a737e317bcfc1e74f68320da1ef"}], "link": ["mods/coc/time-out.rar"], "file_urls": ["http://www.cnmods.org/mods/coc/time-out.rar"], "title": ["\u65f6\u5149\u4e4b\u5916"]},
{"files": [{"url": "http://www.cnmods.org/mods/coc/godHospital.zip", "path": "full/f699ad899363d588070ed76f5bdfd685b9f63925.zip", "checksum": "e2220e7b3ece9f4afc81eca8f868b243"}], "link": ["mods/coc/godHospital.zip"], "file_urls": ["http://www.cnmods.org/mods/coc/godHospital.zip"], "title": ["\u795e\u8d66\u533b\u9662"]},
{"files": [{"url": "http://www.cnmods.org/mods/dnd/hotPlague.zip", "path": "full/78dd7b355395f20883bbad397208ffe1204c0375.zip", "checksum": "a9529e62769ad5f5e9c998235542b1be"}], "link": ["mods/dnd/hotPlague.zip"], "file_urls": ["http://www.cnmods.org/mods/dnd/hotPlague.zip"], "title": ["\u70ed\u761f"]},
{"files": [{"url": "http://www.cnmods.org/mods/dnd/The_murderer.rar", "path": "full/ee3579026a8178595c1d41be9ec4184cb0796b32.rar", "checksum": "85c2254b7ad413e7910d55427dde1025"}], "link": ["mods/dnd/The_murderer.rar"], "file_urls": ["http://www.cnmods.org/mods/dnd/The_murderer.rar"], "title": ["\u8c01\u662f\u771f\u51f6"]},
{"files": [{"url": "http://www.cnmods.org/mods/dnd/The_castle.rar", "path": "full/7c8ade73a137c0ebb4b0f9ba3128259722966303.rar", "checksum": "b11f0f3d735c12e03c6a4ed5b0f7f587"}], "link": ["mods/dnd/The_castle.rar"], "file_urls": ["http://www.cnmods.org/mods/dnd/The_castle.rar"], "title": ["\u53e4\u5821\u60ca\u9b42"]},
{"files": [{"url": "http://www.cnmods.org/mods/dnd/1stdwarf.rar", "path": "full/22cc4bf72eefccaea279b554182317933d54df89.rar", "checksum": "3bd03b4f8b085f221cb615de7b8098b9"}], "link": ["mods/dnd/1stdwarf.rar"], "file_urls": ["http://www.cnmods.org/mods/dnd/1stdwarf.rar"], "title": ["\u5e8f\u7ae0\uff1a\u77ee\u4eba\u9675\u5893\u4e4b\u8c1c"]},
{"files": [{"url": "http://www.cnmods.org/mods/dnd/L&D-V1.zip", "path": "full/dd2c487af3a15a49c7af1cdd9e05e2708e8517cf.zip", "checksum": "7b67b64f73827676868771a94b9af263"}], "link": ["mods/dnd/L&D-V1.zip"], "file_urls": ["http://www.cnmods.org/mods/dnd/L&D-V1.zip"], "title": ["\u5149\u4e0e\u6697"]},
{"files": [{"url": "http://www.cnmods.org/mods/dnd/Warehouse.rar", "path": "full/13f5140f776dd208c8aac3a15180ef2cd0545a5d.rar", "checksum": "5ec6739f3b1fc159661e2289e100485a"}], "link": ["mods/dnd/Warehouse.rar"], "file_urls": ["http://www.cnmods.org/mods/dnd/Warehouse.rar"], "title": ["\u5e9f\u571f\u6b8b\u751f\uff1a\u5c71\u95f4\u4ed3\u5e93"]},
{"files": [{"url": "http://www.cnmods.org/mods/coc/WarIIblack.rar", "path": "full/dcfe1659e3bf2c582faa01dd713293b945f686f5.rar", "checksum": "0ef73c5320ff129fa4a607ae2a90536b"}], "link": ["mods/coc/WarIIblack.rar"], "file_urls": ["http://www.cnmods.org/mods/coc/WarIIblack.rar"], "title": ["\u9ed1\u8272\u884c\u52a8"]},
{"files": [{"url": "http://www.cnmods.org/mods/coc/fire.zip", "path": "full/e073a065b2590476cd24982f72560fda6fd11ef6.zip", "checksum": "3bfd529c344ba88287009217be8cbfe1"}], "link": ["mods/coc/fire.zip"], "file_urls": ["http://www.cnmods.org/mods/coc/fire.zip"], "title": ["\u5730\u72f1\u4e4b\u706b"]},
{"files": [{"url": "http://www.cnmods.org/mods/dnd/Mercury-V1.zip", "path": "full/745624526dc33b1824b469a2bd3522ca5f120e88.zip", "checksum": "b46e840c6267701c0d63239ab280d345"}], "link": ["mods/dnd/Mercury-V1.zip"], "file_urls": ["http://www.cnmods.org/mods/dnd/Mercury-V1.zip"], "title": ["\u4e00\u6ef4\u6c34\u94f6"]},
{"files": [{"url": "http://www.cnmods.org/mods/coc/TheGardenofEarthlyDelights.rar", "path": "full/38e4e891e86f1d9ce1beda76801cdfcc294b1df1.rar", "checksum": "5b04844eb4f6306f29ed777383fbafd1"}], "link": ["mods/coc/TheGardenofEarthlyDelights.rar"], "file_urls": ["http://www.cnmods.org/mods/coc/TheGardenofEarthlyDelights.rar"], "title": ["\u4eba\u95f4\u4e50\u571f"]},
{"files": [{"url": "http://www.cnmods.org/mods/coc/stone.zip", "path": "full/7dddb96deb4ed1fa5c09bf7b9afa6a5edf1d933c.zip", "checksum": "af47b50ddd6b6fd40e0ee09ef232233d"}], "link": ["mods/coc/stone.zip"], "file_urls": ["http://www.cnmods.org/mods/coc/stone.zip"], "title": ["\u5669\u68a6\u4e4b\u77f3"]},
{"files": [{"url": "http://www.cnmods.org/mods/coc/cocdj.zip", "path": "full/661e5a1047984822f008c38e9d9db8866eceb318.zip", "checksum": "2dcbe9e5f2d2dbc8db27f6c84316e054"}], "link": ["mods/coc/cocdj.zip"], "file_urls": ["http://www.cnmods.org/mods/coc/cocdj.zip"], "title": ["\u8d4c\u5c40"]},
{"files": [{"url": "http://www.cnmods.org/mods/coc/Cold_Harvest.rar", "path": "full/72273fc49e737fedb002c1d4700166a832b62d91.rar", "checksum": "b6057f6222427f1589b93cbf8ceed679"}], "link": ["mods/coc/Cold_Harvest.rar"], "file_urls": ["http://www.cnmods.org/mods/coc/Cold_Harvest.rar"], "title": ["\u51b0\u51b7\u7684\u6536\u83b7"]},
{"files": [{"url": "http://www.cnmods.org/mods/TheEmptyRoom.rar", "path": "full/0741f885234e8d5544fb9e1eeb9a4cdaaf5fd779.rar", "checksum": "0332932a8818ef501f1dc595779b0012"}], "link": ["mods/TheEmptyRoom.rar"], "file_urls": ["http://www.cnmods.org/mods/TheEmptyRoom.rar"], "title": ["\u7a7a\u623f\u5b50"]},
{"files": [{"url": "http://www.cnmods.org/mods/dnd/onefqkk.zip", "path": "full/db214c1d43c86764db9aa758a237d4e9b153f423.zip", "checksum": "a07e5dbe1c417847d7558a4d0a788f89"}], "link": ["mods/dnd/onefqkk.zip"], "file_urls": ["http://www.cnmods.org/mods/dnd/onefqkk.zip"], "title": ["\u4e00\u4e2a\u5e9f\u5f03\u77ff\u5751"]},
{"files": [{"url": "http://www.cnmods.org/mods/dnd/4E-Disaster.zip", "path": "full/c0908520e912bdaa9600f2adf9f790e35edef784.zip", "checksum": "e72814b627747b224c0ad6c5e607e514"}], "link": ["mods/dnd/4E-Disaster.zip"], "file_urls": ["http://www.cnmods.org/mods/dnd/4E-Disaster.zip"], "title": ["\u5305\u85cf\u7978\u5fc3"]},
{"files": [{"url": "http://www.cnmods.org/mods/coc/TheKingofShredsandPatches.rar", "path": "full/9530ac49045571447e7d1120d0006c10298d9572.rar", "checksum": "7a9ef4b5040eebd4f37f77aceff7d849"}], "link": ["mods/coc/TheKingofShredsandPatches.rar"], "file_urls": ["http://www.cnmods.org/mods/coc/TheKingofShredsandPatches.rar"], "title": ["\u8934\u891b\u4e4b\u738b"]},
{"files": [{"url": "http://www.cnmods.org/mods/dnd/Pit-V1.zip", "path": "full/8075799aaa5096dfec2939b2d3a09a6555fb764f.zip", "checksum": "05b5cb64361a43c95575242bc464d791"}], "link": ["mods/dnd/Pit-V1.zip"], "file_urls": ["http://www.cnmods.org/mods/dnd/Pit-V1.zip"], "title": ["\u77ff\u5751"]},
{"files": [{"url": "http://www.cnmods.org/mods/coc/Lozdra.rar", "path": "full/81cb0806ab053a1f6e5d73d54c89b5446bf40c3b.rar", "checksum": "942d2b93391fde8aaf03e061231a2b47"}], "link": ["mods/coc/Lozdra.rar"], "file_urls": ["http://www.cnmods.org/mods/coc/Lozdra.rar"], "title": ["\u6d1b\u5179\u5fb7\u62c9"]},
{"files": [{"url": "http://www.cnmods.org/mods/coc/sailasebook.rar", "path": "full/23d82f6f5fc19d737cacbb6694f7668d5b29a69e.rar", "checksum": "febee1f92527494b60c8a8f8a8c1542c"}], "link": ["mods/coc/sailasebook.rar"], "file_urls": ["http://www.cnmods.org/mods/coc/sailasebook.rar"], "title": ["\u585e\u62c9\u65af\u7684\u4e66"]},
{"files": [{"url": "http://www.cnmods.org/mods/dnd/AnIcyHeart.rar", "path": "full/e80477845331e6084b5135f0d405c876369b05c6.rar", "checksum": "5e47062aac9339402f02cd4214118a81"}], "link": ["mods/dnd/AnIcyHeart.rar"], "file_urls": ["http://www.cnmods.org/mods/dnd/AnIcyHeart.rar"], "title": ["\u5bd2\u51b0\u4e4b\u5fc3"]},
{"files": [{"url": "http://www.cnmods.org/mods/dnd/witching_season_ch.rar", "path": "full/04449d40faecba95ba47ececa7a6d88c6483b6f3.rar", "checksum": "a3660586271ec54478f5342358dd70d9"}], "link": ["mods/dnd/witching_season_ch.rar"], "file_urls": ["http://www.cnmods.org/mods/dnd/witching_season_ch.rar"], "title": ["\u5deb\u5a46\u8fdb\u884c\u65f6"]},
{"files": [{"url": "http://www.cnmods.org/mods/dnd/shipofhorror.rar", "path": "full/7705facedc91ba6b59eef3889754d8e6dd412971.rar", "checksum": "4430572551495b42b3fd3be671c60108"}], "link": ["mods/dnd/shipofhorror.rar"], "file_urls": ["http://www.cnmods.org/mods/dnd/shipofhorror.rar"], "title": ["\u6050\u60e7\u4e4b\u8239"]},
{"files": [{"url": "http://www.cnmods.org/mods/coc/SweetHome.rar", "path": "full/95fa894ff84d2e05d44d8b27fca82296af3ee4ff.rar", "checksum": "cad6ba1ac22fb87ac9b8d6b53d5cb99b"}], "link": ["mods/coc/SweetHome.rar"], "file_urls": ["http://www.cnmods.org/mods/coc/SweetHome.rar"], "title": ["\u5316\u77f3"]},
{"files": [{"url": "http://www.cnmods.org/mods/coc/bookstore.rar", "path": "full/5a128613a2f9a9fd032fbd0304e16307d84c3d9a.rar", "checksum": "c894721601e537be1cedfa66120b6297"}], "link": ["mods/coc/bookstore.rar"], "file_urls": ["http://www.cnmods.org/mods/coc/bookstore.rar"], "title": ["\u4e66\u5e97"]},
{"files": [{"url": "http://www.cnmods.org/mods/dnd/yrgoril.zip", "path": "full/3c892ac22de91c7ce97c5e8e401b87c529a64bc5.zip", "checksum": "00f8657f2b97464913532abf6e245f6b"}], "link": ["mods/dnd/yrgoril.zip"], "file_urls": ["http://www.cnmods.org/mods/dnd/yrgoril.zip"], "title": ["\u6781\u57df\u51b0\u539f"]},
{"files": [{"url": "http://www.cnmods.org/mods/dnd/omegach.rar", "path": "full/7da18b6ded4581e3d088bdd652fcdc009d29aa5e.rar", "checksum": "f2eac19ec67fc5db214ab2a370633867"}], "link": ["mods/dnd/omegach.rar"], "file_urls": ["http://www.cnmods.org/mods/dnd/omegach.rar"], "title": ["\u7ec8\u7ed3\u4e4b\u59cb"]},
{"files": [{"url": "http://www.cnmods.org/mods/coc/tote.rar", "path": "full/47b99cb7686b3a4c8327620cf8924faaee6b21e1.rar", "checksum": "abb2818cd4b041b0b83d8e7e50aa3670"}], "link": ["mods/coc/tote.rar"], "file_urls": ["http://www.cnmods.org/mods/coc/tote.rar"], "title": ["\u900f\u7279\u7684\u5315\u9996"]},
{"files": [{"url": "http://www.cnmods.org/mods/coc/deepdream.rar", "path": "full/d8b11cbcc5704763727c9a12d26bd3e43c8d4a57.rar", "checksum": "b35827f29e49634901e93350e96a4a84"}], "link": ["mods/coc/deepdream.rar"], "file_urls": ["http://www.cnmods.org/mods/coc/deepdream.rar"], "title": ["\u6700\u6df1\u7684\u68a6\u5883"]},
{"files": [{"url": "http://www.cnmods.org/mods/coc/drakby.rar", "path": "full/88ebab146c0f6030d9d632c01a8cbaf19153aaf1.rar", "checksum": "ab92b7d3ef27c0ad59ef5f0decfb5d6d"}], "link": ["mods/coc/drakby.rar"], "file_urls": ["http://www.cnmods.org/mods/coc/drakby.rar"], "title": ["\u9ed1\u6697\u8fb9\u7f18"]},
{"files": [{"url": "http://www.cnmods.org/mods/dnd/rogue.rar", "path": "full/a26d594cca86acb056355a25ec00abe7782b9b68.rar", "checksum": "6941206d610feb2b8e8cf3f7b355494c"}], "link": ["mods/dnd/rogue.rar"], "file_urls": ["http://www.cnmods.org/mods/dnd/rogue.rar"], "title": ["\u9634\u5f71\u4e2d\u7684\u5229\u5203"]},
{"files": [{"url": "http://www.cnmods.org/mods/coc/three.rar", "path": "full/00d8866fb57677be85e40c25cb4699955f2465bd.rar", "checksum": "67f7e958372fdeda237d004c3d64645d"}], "link": ["mods/coc/three.rar"], "file_urls": ["http://www.cnmods.org/mods/coc/three.rar"], "title": ["\u4e09\u6869\u60b2\u5267"]},
{"files": [{"url": "http://www.cnmods.org/mods/dnd/supernatural.rar", "path": "full/6729f0d1f92bfde4006b79fed7236da371bbc2b7.rar", "checksum": "b77a7d621c7b78a1068199b68e189374"}], "link": ["mods/dnd/supernatural.rar"], "file_urls": ["http://www.cnmods.org/mods/dnd/supernatural.rar"], "title": ["\u7075\u5f02\u6863\u6848"]},
{"files": [{"url": "http://www.cnmods.org/mods/coc/dogblood.rar", "path": "full/f6ee85210106d88595c12cefce3929c32a491834.rar", "checksum": "74367987bed9ff6e118699509e845db7"}], "link": ["mods/coc/dogblood.rar"], "file_urls": ["http://www.cnmods.org/mods/coc/dogblood.rar"], "title": ["\u8150\u574f\u4e4b\u8840"]},
{"files": [{"url": "http://www.cnmods.org/mods/coc/tellme.zip", "path": "full/3732ff2e10add20d1240f27b208c9abfb967507f.zip", "checksum": "b908110b7696175b15d4a1acdd0b0180"}], "link": ["mods/coc/tellme.zip"], "file_urls": ["http://www.cnmods.org/mods/coc/tellme.zip"], "title": ["\u9ec4\u8863\u4e4b\u738b"]},
{"files": [{"url": "http://www.cnmods.org/mods/coc/unegg.rar", "path": "full/bce926825f2e3bc93f5d143e065c50c100fdd999.rar", "checksum": "7db8418b4cf314716cd11329714822b3"}], "link": ["mods/coc/unegg.rar"], "file_urls": ["http://www.cnmods.org/mods/coc/unegg.rar"], "title": ["\u8fdc\u53e4\u4e4b\u5375"]},
{"files": [{"url": "http://www.cnmods.org/mods/dnd/halfnight.rar", "path": "full/daa2f678ff573f123c8b04795a138779d6f295c7.rar", "checksum": "2c7870bed847785bb83e1b7bbab3b941"}], "link": ["mods/dnd/halfnight.rar"], "file_urls": ["http://www.cnmods.org/mods/dnd/halfnight.rar"], "title": ["\u591c\u4f34\u54ed\u58f0"]},
{"files": [{"url": "http://www.cnmods.org/mods/dnd/gamefs.rar", "path": "full/394446f9d362678c2a281aa91d6caae8b6d209c6.rar", "checksum": "75a62ceb9ee46f224f47347a09b481bb"}], "link": ["mods/dnd/gamefs.rar"], "file_urls": ["http://www.cnmods.org/mods/dnd/gamefs.rar"], "title": ["\u620f\u6cd5\u5e08"]},
{"files": [{"url": "http://www.cnmods.org/mods/dnd/jorke.rar", "path": "full/3064c1c0073596f92e5acfa6269e3e498b2c9ea4.rar", "checksum": "ff6db5ddf73211871c65034e14410364"}], "link": ["mods/dnd/jorke.rar"], "file_urls": ["http://www.cnmods.org/mods/dnd/jorke.rar"], "title": ["\u724c\u5c40"]},
{"files": [{"url": "http://www.cnmods.org/mods/dnd/smalltown.rar", "path": "full/35f89e6373d00dacdda435b500493507d54a6440.rar", "checksum": "ab4aa88d335a696c278d24fde165b1ba"}], "link": ["mods/dnd/smalltown.rar"], "file_urls": ["http://www.cnmods.org/mods/dnd/smalltown.rar"], "title": ["\u5c0f\u5854\u4e4b\u5f79"]},
{"files": [{"url": "http://www.cnmods.org/mods/dnd/buildfor.rar", "path": "full/4eaee34a1cd7f2325b3e88530e19ba64db3ff0b3.rar", "checksum": "5cf3a5e0dd08b14ba4acec7e56f5b2da"}], "link": ["mods/dnd/buildfor.rar"], "file_urls": ["http://www.cnmods.org/mods/dnd/buildfor.rar"], "title": ["\u5efa\u7b51\u6c38\u6052"]},
{"files": [{"url": "http://www.cnmods.org/mods/dnd/wailingcaverns.zip", "path": "full/d9db6358875872f070b69a95042a5c850782df18.zip", "checksum": "0fb984121a5689ab3e3a5a5d6bdb42a2"}], "link": ["mods/dnd/wailingcaverns.zip"], "file_urls": ["http://www.cnmods.org/mods/dnd/wailingcaverns.zip"], "title": ["\u54c0\u568e\u6d1e\u7a74"]},
{"files": [{"url": "http://www.cnmods.org/mods/dnd/showth_death.rar", "path": "full/8804926babaeb191b14b192b678e4f999206cf66.rar", "checksum": "be0d5be5b2bffdb0f4a130f8e598edb1"}], "link": ["mods/dnd/showth_death.rar"], "file_urls": ["http://www.cnmods.org/mods/dnd/showth_death.rar"], "title": ["\u5f71\u4e4b\u5893\u7a74"]},
{"files": [{"url": "http://www.cnmods.org/mods/dnd/155sleep.rar", "path": "full/6d05cfd60fafcc5f38d535995c672d558fab54eb.rar", "checksum": "ccc6c5faf54458bb96131c721d2b7eaa"}], "link": ["mods/dnd/155sleep.rar"], "file_urls": ["http://www.cnmods.org/mods/dnd/155sleep.rar"], "title": ["\u68a6\u51a2\u6c89\u7761\u8005"]},
{"files": [{"url": "http://www.cnmods.org/mods/dnd/jialindx.rar", "path": "full/dae567eeef52368234148ed552ddb68abe32affa.rar", "checksum": "3b1d7256f0669423020b31e49f6e3165"}], "link": ["mods/dnd/jialindx.rar"], "file_urls": ["http://www.cnmods.org/mods/dnd/jialindx.rar"], "title": ["\u5730\u4e0b\u795e\u6bbf\u7684\u79d8\u5bc6"]},
{"files": [{"url": "http://www.cnmods.org/mods/dnd/3e_ghosthouse.rar", "path": "full/6cc9ffd6e2866db7444d543630db8f1cabb205e3.rar", "checksum": "4bd0bb89ec6f2c6ad48c30153172943c"}], "link": ["mods/dnd/3e_ghosthouse.rar"], "file_urls": ["http://www.cnmods.org/mods/dnd/3e_ghosthouse.rar"], "title": ["\u9b3c\u5c4b\u9b54\u5f71"]},
{"files": [{"url": "http://www.cnmods.org/mods/dnd/dragonsgoblin.rar", "path": "full/7352e2e158f078fa7b5aed9e991b1598025a6c98.rar", "checksum": "af1f4aecb138d5b0326816766cd9737e"}], "link": ["mods/dnd/dragonsgoblin.rar"], "file_urls": ["http://www.cnmods.org/mods/dnd/dragonsgoblin.rar"], "title": ["\u9752\u7ea2\u7682\u767d"]},
{"files": [{"url": "http://www.cnmods.org/mods/dnd/3e_blood.rar", "path": "full/63a3047c28f15b57e4aa1d0c3748059fdd1b5b5f.rar", "checksum": "65994782c8635c0137e8537704378d13"}], "link": ["mods/dnd/3e_blood.rar"], "file_urls": ["http://www.cnmods.org/mods/dnd/3e_blood.rar"], "title": ["\u8840\u503a\u8840\u507f"]},
{"files": [{"url": "http://www.cnmods.org/mods/dnd/3e_onedre.rar", "path": "full/4cac4413905ae44893b20979de8e71d28002d791.rar", "checksum": "62a389b57d976abfd46a6500ea40085e"}], "link": ["mods/dnd/3e_onedre.rar"], "file_urls": ["http://www.cnmods.org/mods/dnd/3e_onedre.rar"], "title": ["\u91ce\u6027\u7684\u547c\u5524"]},
{"files": [{"url": "http://www.cnmods.org/mods/coc/art-of-madness-ch.zip", "path": "full/69bf3efdf9a10e1e073704a02a6d44c08bfde06f.zip", "checksum": "ef5a3a57e5f8c5ea5b33c7ab857dd87a"}], "link": ["mods/coc/art-of-madness-ch.zip"], "file_urls": ["http://www.cnmods.org/mods/coc/art-of-madness-ch.zip"], "title": ["\u75af\u72c2\u7684\u827a\u672f"]},
{"files": [{"url": "http://www.cnmods.org/mods/dnd/fqsz_f.rar", "path": "full/01cdabb4833749465ad9002289b55a27f78251a5.rar", "checksum": "21a5eac84bf7958c70fc45a8cb762908"}], "link": ["mods/dnd/fqsz_f.rar"], "file_urls": ["http://www.cnmods.org/mods/dnd/fqsz_f.rar"], "title": ["\u5e9f\u5f03\u54e8\u7ad9"]},
{"files": [{"url": "http://www.cnmods.org/mods/coc/Tree.rar", "path": "full/6f37e73a69da3505ffd2081e880cfd3a35890553.rar", "checksum": "7da2557c07ff1025d1fab71eda681777"}], "link": ["mods/coc/Tree.rar"], "file_urls": ["http://www.cnmods.org/mods/coc/Tree.rar"], "title": ["\u6797\u4e2d\u9634\u5f71"]},
{"files": [{"url": "http://www.cnmods.org/mods/dnd/tengoblin.zip", "path": "full/090d22925126a9080222292ff181282227012a1e.zip", "checksum": "798a3caf15907aa62532e219f3031266"}], "link": ["mods/dnd/tengoblin.zip"], "file_urls": ["http://www.cnmods.org/mods/dnd/tengoblin.zip"], "title": ["\u5341\u9547\u51ac\u65e5"]},
{"files": [{"url": "http://www.cnmods.org/mods/coc/Heaven.rar", "path": "full/2fce7454489ed7639e0678a9aabe7d16c4985c54.rar", "checksum": "5fa3cbcc114b923d7aba1e589449c924"}], "link": ["mods/coc/Heaven.rar"], "file_urls": ["http://www.cnmods.org/mods/coc/Heaven.rar"], "title": ["\u5929\u5802\u4e4b\u6c34"]},
{"files": [{"url": "http://www.cnmods.org/mods/dnd/blackrose.zip", "path": "full/dcb4fbe72c810b62f3f4bb40fdc460365368b7dc.zip", "checksum": "80f87add27768305d189e6cc8bb879b3"}], "link": ["mods/dnd/blackrose.zip"], "file_urls": ["http://www.cnmods.org/mods/dnd/blackrose.zip"], "title": ["\u9b54\u57df\u4f20\u5947-\u5f53\u9ed1\u73ab\u7470\u76db\u5f00\u65f6"]},
{"files": [{"url": "http://www.cnmods.org/mods/dnd/3emonk.zip", "path": "full/f6c6a261803a086c204fdaa5f1311faec415fc87.zip", "checksum": "41019b02fa6096e55c452998378ebc13"}], "link": ["mods/dnd/3emonk.zip"], "file_urls": ["http://www.cnmods.org/mods/dnd/3emonk.zip"], "title": ["\u65e0\u5c3d\u7684\u4fee\u884c"]}]